{"v":"5.6.3","fr":30,"ip":35,"op":72,"w":640,"h":360,"nm":"3 dots loading -2- 640x360","ddd":0,"assets":[],"layers":[{"ddd":0,"ind":3,"ty":3,"nm":"Null 31","sr":1,"ks":{"o":{"a":0,"k":0,"ix":11},"r":{"a":0,"k":0,"ix":10},"p":{"a":0,"k":[313,-98,0],"ix":2},"a":{"a":0,"k":[50,50,0],"ix":1},"s":{"a":0,"k":[100,100,100],"ix":6}},"ao":0,"ip":0,"op":121,"st":0,"bm":0},{"ddd":0,"ind":4,"ty":4,"nm":"Shape Layer 34","sr":1,"ks":{"o":{"a":0,"k":100,"ix":11},"r":{"a":0,"k":0,"ix":10},"p":{"a":1,"k":[{"i":{"x":0.667,"y":1},"o":{"x":0.167,"y":0},"t":35,"s":[474.46,182.56,0],"to":[0,0,0],"ti":[0,0,0]},{"i":{"x":0,"y":1},"o":{"x":0.333,"y":0},"t":41,"s":[474.46,192.56,0],"to":[0,0,0],"ti":[0,0,0]},{"i":{"x":0.667,"y":1},"o":{"x":0.804,"y":0.011},"t":49,"s":[474.46,60.77,0],"to":[0,0,0],"ti":[0,0,0]},{"i":{"x":0.667,"y":1},"o":{"x":0.333,"y":0},"t":62,"s":[474.46,198.89,0],"to":[0,0,0],"ti":[0,0,0]},{"i":{"x":0.667,"y":1},"o":{"x":0.333,"y":0},"t":68,"s":[474.46,157.848,0],"to":[0,0,0],"ti":[0,0,0]},{"i":{"x":0.667,"y":1},"o":{"x":0.333,"y":0},"t":74,"s":[474.46,189.56,0],"to":[0,0,0],"ti":[0,0,0]},{"t":78,"s":[474.46,182.56,0]}],"ix":2},"a":{"a":0,"k":[-87.281,-91.281,0],"ix":1},"s":{"a":0,"k":[153,153,100],"ix":6}},"ao":0,"shapes":[{"ty":"gr","it":[{"ty":"gr","it":[{"d":1,"ty":"el","s":{"a":0,"k":[41.438,41.438],"ix":2},"p":{"a":0,"k":[0,0],"ix":3},"nm":"Ellipse Path 1","mn":"ADBE Vector Shape - Ellipse","hd":false},{"ty":"fl","c":{"a":0,"k":[0.8,0.811764705882,1,1],"ix":4},"o":{"a":0,"k":100,"ix":5},"r":1,"bm":0,"nm":"Fill 1","mn":"ADBE Vector Graphic - Fill","hd":false},{"ty":"tr","p":{"a":0,"k":[-105.281,-92.844],"ix":2},"a":{"a":0,"k":[0,0],"ix":1},"s":{"a":0,"k":[130,130],"ix":3},"r":{"a":0,"k":0,"ix":6},"o":{"a":0,"k":100,"ix":7},"sk":{"a":0,"k":0,"ix":4},"sa":{"a":0,"k":0,"ix":5},"nm":"Transform"}],"nm":"Ellipse 1","np":2,"cix":2,"bm":0,"ix":1,"mn":"ADBE Vector Group","hd":false},{"ty":"tr","p":{"a":0,"k":[-105.281,-92.844],"ix":2},"a":{"a":0,"k":[-105.281,-92.844],"ix":1},"s":{"a":0,"k":[100,100],"ix":3},"r":{"a":0,"k":0,"ix":6},"o":{"a":0,"k":100,"ix":7},"sk":{"a":0,"k":0,"ix":4},"sa":{"a":0,"k":0,"ix":5},"nm":"Transform"}],"nm":"Group 1","np":1,"cix":2,"bm":0,"ix":1,"mn":"ADBE Vector Group","hd":false}],"ip":35,"op":78,"st":6,"bm":0},{"ddd":0,"ind":5,"ty":4,"nm":"Shape Layer 33","parent":3,"sr":1,"ks":{"o":{"a":0,"k":100,"ix":11},"r":{"a":0,"k":0,"ix":10},"p":{"a":1,"k":[{"i":{"x":0.817,"y":0},"o":{"x":0.327,"y":0.142},"t":35,"s":[84.46,337.555,0],"to":[0,0,0],"ti":[0,0,0]},{"i":{"x":0,"y":1},"o":{"x":0.167,"y":0.055},"t":38,"s":[84.46,340.56,0],"to":[0,0,0],"ti":[0,0,0]},{"i":{"x":0.833,"y":0.833},"o":{"x":0.804,"y":0.01},"t":46,"s":[84.46,208.77,0],"to":[0,0,0],"ti":[0,0,0]},{"i":{"x":0.243,"y":1},"o":{"x":0.167,"y":0.167},"t":59,"s":[84.46,349.89,0],"to":[0,0,0],"ti":[0,0,0]},{"i":{"x":0.667,"y":0.675},"o":{"x":0.333,"y":0},"t":65,"s":[84.46,301.176,0],"to":[0,0,0],"ti":[0,0,0]},{"i":{"x":0.725,"y":0.096},"o":{"x":0.199,"y":0.653},"t":72,"s":[84.46,340.56,0],"to":[0,0,0],"ti":[0,0,0]},{"t":78,"s":[84.46,330.56,0]}],"ix":2},"a":{"a":0,"k":[-87.281,-91.281,0],"ix":1},"s":{"a":0,"k":[153,153,100],"ix":6}},"ao":0,"shapes":[{"ty":"gr","it":[{"ty":"gr","it":[{"d":1,"ty":"el","s":{"a":0,"k":[41.438,41.438],"ix":2},"p":{"a":0,"k":[0,0],"ix":3},"nm":"Ellipse Path 1","mn":"ADBE Vector Shape - Ellipse","hd":false},{"ty":"fl","c":{"a":0,"k":[1,0.352941176471,0,1],"ix":4},"o":{"a":0,"k":100,"ix":5},"r":1,"bm":0,"nm":"Fill 1","mn":"ADBE Vector Graphic - Fill","hd":false},{"ty":"tr","p":{"a":0,"k":[-105.281,-92.844],"ix":2},"a":{"a":0,"k":[0,0],"ix":1},"s":{"a":0,"k":[130,130],"ix":3},"r":{"a":0,"k":0,"ix":6},"o":{"a":0,"k":100,"ix":7},"sk":{"a":0,"k":0,"ix":4},"sa":{"a":0,"k":0,"ix":5},"nm":"Transform"}],"nm":"Ellipse 1","np":2,"cix":2,"bm":0,"ix":1,"mn":"ADBE Vector Group","hd":false},{"ty":"tr","p":{"a":0,"k":[-105.281,-92.844],"ix":2},"a":{"a":0,"k":[-105.281,-92.844],"ix":1},"s":{"a":0,"k":[100,100],"ix":3},"r":{"a":0,"k":0,"ix":6},"o":{"a":0,"k":100,"ix":7},"sk":{"a":0,"k":0,"ix":4},"sa":{"a":0,"k":0,"ix":5},"nm":"Transform"}],"nm":"Group 1","np":1,"cix":2,"bm":0,"ix":1,"mn":"ADBE Vector Group","hd":false}],"ip":35,"op":77,"st":3,"bm":0},{"ddd":0,"ind":6,"ty":4,"nm":"Shape Layer 25","sr":1,"ks":{"o":{"a":0,"k":100,"ix":11},"r":{"a":0,"k":0,"ix":10},"p":{"a":1,"k":[{"i":{"x":0.667,"y":1},"o":{"x":0.167,"y":0},"t":33,"s":[220.46,182.56,0],"to":[0,0,0],"ti":[0,0,0]},{"i":{"x":0,"y":1},"o":{"x":0.248,"y":0},"t":35,"s":[220.46,195.84,0],"to":[0,0,0],"ti":[0,0,0]},{"i":{"x":0.833,"y":0.833},"o":{"x":0.804,"y":0.009},"t":43,"s":[220.46,60.77,0],"to":[0,0,0],"ti":[0,0,0]},{"i":{"x":0.667,"y":1},"o":{"x":0.167,"y":0.167},"t":56,"s":[220.46,219.89,0],"to":[0,0,0],"ti":[0,0,0]},{"i":{"x":0.667,"y":1},"o":{"x":0.333,"y":0},"t":62,"s":[220.46,153.176,0],"to":[0,0,0],"ti":[0,0,0]},{"i":{"x":0.702,"y":1},"o":{"x":0.181,"y":0},"t":70,"s":[220.46,198.56,0],"to":[0,0,0],"ti":[0,0,0]},{"t":79,"s":[220.46,182.56,0]}],"ix":2},"a":{"a":0,"k":[-87.281,-91.281,0],"ix":1},"s":{"a":0,"k":[153,153,100],"ix":6}},"ao":0,"shapes":[{"ty":"gr","it":[{"ty":"gr","it":[{"d":1,"ty":"el","s":{"a":0,"k":[41.438,41.438],"ix":2},"p":{"a":0,"k":[0,0],"ix":3},"nm":"Ellipse Path 1","mn":"ADBE Vector Shape - Ellipse","hd":false},{"ty":"fl","c":{"a":0,"k":[1,0.929411764706,0.698039215686,1],"ix":4},"o":{"a":0,"k":100,"ix":5},"r":1,"bm":0,"nm":"Fill 1","mn":"ADBE Vector Graphic - Fill","hd":false},{"ty":"tr","p":{"a":0,"k":[-105.281,-92.844],"ix":2},"a":{"a":0,"k":[0,0],"ix":1},"s":{"a":0,"k":[130,130],"ix":3},"r":{"a":0,"k":0,"ix":6},"o":{"a":0,"k":100,"ix":7},"sk":{"a":0,"k":0,"ix":4},"sa":{"a":0,"k":0,"ix":5},"nm":"Transform"}],"nm":"Ellipse 1","np":2,"cix":2,"bm":0,"ix":1,"mn":"ADBE Vector Group","hd":false},{"ty":"tr","p":{"a":0,"k":[-105.281,-92.844],"ix":2},"a":{"a":0,"k":[-105.281,-92.844],"ix":1},"s":{"a":0,"k":[100,100],"ix":3},"r":{"a":0,"k":0,"ix":6},"o":{"a":0,"k":100,"ix":7},"sk":{"a":0,"k":0,"ix":4},"sa":{"a":0,"k":0,"ix":5},"nm":"Transform"}],"nm":"Group 1","np":1,"cix":2,"bm":0,"ix":1,"mn":"ADBE Vector Group","hd":false}],"ip":35,"op":79,"st":0,"bm":0}],"markers":[]}